{
    "Map": [
        {
            "ADD": "2"
        },
        {
            "ADD": "13"
        },
        {
            "SUB": "12"
        },
        {
            "MUL": "17"
        },
        {
            "SUB": "11"
        },
        {
            "ADD": "18"
        },
        {
            "MUL": "17"
        },
        {
            "SUB": "9"
        },
        {
            "ADD": "8"
        },
        {
            "ADD": "3"
        },
        {
            "MUL": "9"
        },
        {
            "SUB": "11"
        },
        {
            "MUL": "19"
        },
        {
            "SUB": "8"
        },
        {
            "MUL": "15"
        },
        {
            "ADD": "17"
        },
        {
            "ADD": "5"
        },
        {
            "MUL": "7"
        },
        {
            "ADD": "10"
        },
        {
            "ADD": "14"
        },
        {
            "ADD": "19"
        },
        {
            "ADD": "2"
        },
        {
            "SUB": "5"
        },
        {
            "MUL": "8"
        },
        {
            "ADD": "4"
        },
        {
            "ADD": "16"
        },
        {
            "SUB": "11"
        },
        {
            "ADD": "1"
        },
        {
            "ADD": "9"
        },
        {
            "ADD": "17"
        },
        {
            "DIV": "5"
        },
        {
            "ADD": "2"
        },
        {
            "ADD": "3"
        },
        {
            "ADD": "5"
        },
        {
            "SUB": "2"
        },
        {
            "ADD": "19"
        },
        {
            "MUL": "10"
        },
        {
            "ADD": "2"
        },
        {
            "ADD": "12"
        },
        {
            "ADD": "15"
        },
        {
            "MUL": "1"
        },
        {
            "ADD": "15"
        },
        {
            "DIV": "16"
        },
        {
            "ADD": "12"
        },
        {
            "SUB": "1"
        },
        {
            "ADD": "13"
        },
        {
            "ADD": "4"
        },
        {
            "ADD": "9"
        },
        {
            "ADD": "9"
        },
        {
            "ADD": "5"
        },
        {
            "DIV": "16"
        },
        {
            "ADD": "3"
        },
        {
            "ADD": "2"
        },
        {
            "ADD": "3"
        },
        {
            "ADD": "4"
        },
        {
            "MUL": "6"
        },
        {
            "MUL": "12"
        },
        {
            "MUL": "17"
        },
        {
            "SUB": "18"
        },
        {
            "ADD": "7"
        },
        {
            "MUL": "3"
        },
        {
            "DIV": "14"
        },
        {
            "DIV": "4"
        },
        {
            "SUB": "7"
        },
        {
            "SUB": "4"
        },
        {
            "ADD": "14"
        },
        {
            "ADD": "4"
        },
        {
            "ADD": "7"
        },
        {
            "ADD": "15"
        },
        {
            "ADD": "5"
        },
        {
            "DIV": "4"
        },
        {
            "MUL": "6"
        },
        {
            "DIV": "13"
        },
        {
            "MUL": "2"
        },
        {
            "ADD": "1"
        },
        {
            "SUB": "11"
        },
        {
            "ADD": "8"
        },
        {
            "ADD": "15"
        },
        {
            "ADD": "18"
        },
        {
            "ADD": "1"
        },
        {
            "ADD": "14"
        },
        {
            "ADD": "7"
        },
        {
            "SUB": "5"
        },
        {
            "ADD": "11"
        },
        {
            "SUB": "15"
        },
        {
            "ADD": "7"
        }
    ],
    "Reduce": {
        "REDUCESUB": "NULL"
    },
    "Chunks": 21
}